{
  "title": "第 15 集 野餐！| Picnic!",
  "data": [
    {
      "zh": "野餐！",
      "en": "Picnic!",
      "startTime": 21.198,
      "duration": 0.5470000000000006
    },
    {
      "zh": "今天是个阳光明媚的好日子。",
      "en": "It is a lovely bright, sunny day.",
      "startTime": 25.658,
      "duration": 2.293999999999997
    },
    {
      "zh": "佩奇和她的家人外出野餐！",
      "en": "Peppa and her family are going for a picnic!",
      "startTime": 28.027,
      "duration": 2.2659999999999982
    },
    {
      "zh": "猪爸爸带着野餐篮。",
      "en": "Daddy Pig is bringing the picnic basket.",
      "startTime": 30.529,
      "duration": 2.352999999999998
    },
    {
      "zh": "野餐布，面包，奶酪，蕃茄和柠檬汽水。",
      "en": "Picnic-blanket, bread, cheese, tomatoes and lemonade.",
      "startTime": 32.965,
      "duration": 4.803999999999995
    },
    {
      "zh": "有没有什么东西我们忘记了？",
      "en": "Is there anything we've forgotten?",
      "startTime": 38.037,
      "duration": 2.2210000000000036
    },
    {
      "zh": "妈妈的草莓蛋糕！",
      "en": "Mummy's strawberry cake!",
      "startTime": 40.285,
      "duration": 1.8719999999999999
    },
    {
      "zh": "我是在逗你们而已！",
      "en": "I was just teasing!",
      "startTime": 43.35,
      "duration": 1.5399999999999991
    },
    {
      "zh": "妈妈亲手做的草莓蛋糕也在这里。",
      "en": "Mummy's home-made strawberry cake is there, too.",
      "startTime": 45.703,
      "duration": 2.6129999999999995
    },
    {
      "zh": "大家准备好了吗？",
      "en": "Is everybody ready?",
      "startTime": 48.414,
      "duration": 1.5949999999999989
    },
    {
      "zh": "准备好了！",
      "en": "Ready!",
      "startTime": 50.076,
      "duration": 0.732999999999997
    },
    {
      "zh": "那我们出发吧！",
      "en": "Then let's go!",
      "startTime": 50.869,
      "duration": 1.5459999999999994
    },
    {
      "zh": "这个地方看起来很适合我们野餐！",
      "en": "This looks like just the spot for our picnic!",
      "startTime": 61.14,
      "duration": 2.780000000000001
    },
    {
      "zh": "好耶！",
      "en": "Hurray!",
      "startTime": 63.98,
      "duration": 0.8079999999999998
    },
    {
      "zh": "在野外真好！",
      "en": "It's great to be outdoors!",
      "startTime": 69.376,
      "duration": 1.8529999999999944
    },
    {
      "zh": "我们应该稍微跑一下做点运动！",
      "en": "We should run around a bit and get some exercise!",
      "startTime": 71.57,
      "duration": 2.2730000000000103
    },
    {
      "zh": "我想吃点东西，再睡一会。",
      "en": "I want to eat, the have a nap.",
      "startTime": 74.337,
      "duration": 1.926000000000002
    },
    {
      "zh": "我可不想跑来跑去。",
      "en": "I certainly don't want to run around.",
      "startTime": 76.69,
      "duration": 2.234000000000009
    },
    {
      "zh": "也许爸爸应该跑跑。",
      "en": "Maybe Daddy should run around a bit.",
      "startTime": 79.077,
      "duration": 2.5060000000000002
    },
    {
      "zh": "他的肚子太大了。",
      "en": "His tummy is quite big.",
      "startTime": 81.616,
      "duration": 1.507000000000005
    },
    {
      "zh": "我的肚子一点也不大。",
      "en": "My tummy is not big.",
      "startTime": 83.148,
      "duration": 2.2349999999999994
    },
    {
      "zh": "但是过一会儿我会做些运动，即使没有其他人做。",
      "en": "But later, I will get some exercise, even if no one else does.",
      "startTime": 85.517,
      "duration": 4.192999999999998
    },
    {
      "zh": "让我们开吃吧！",
      "en": "Let's eat!",
      "startTime": 90.783,
      "duration": 0.7800000000000011
    },
    {
      "zh": "好主意，猪妈妈！我真的饿了！",
      "en": "Good idea, Mummy Pig! I'm really hungry!",
      "startTime": 91.59,
      "duration": 3.522999999999996
    },
    {
      "zh": "嗯。。。真美味！",
      "en": "Hmmm... delicious!",
      "startTime": 96.803,
      "duration": 2.1000000000000085
    },
    {
      "zh": "我觉得很困！",
      "en": "Ahhhhh! I feel quite sleepy!",
      "startTime": 102.835,
      "duration": 4.1129999999999995
    },
    {
      "zh": "我记得你想到处跑跑的，猪爸爸？",
      "en": "I thought you wanted to run around a bit, Daddy Pig?",
      "startTime": 107.339,
      "duration": 2.882000000000005
    },
    {
      "zh": "过会儿吧。。。",
      "en": "Later...",
      "startTime": 110.581,
      "duration": 1.0249999999999915
    },
    {
      "zh": "瞧！那里的池塘有群小鸭子！",
      "en": "Look! There's a little duck pond!",
      "startTime": 116.615,
      "duration": 2.5530000000000115
    },
    {
      "zh": "妈妈，我们可以喂那些鸭子吗？",
      "en": "Mummy, can we feed the ducks?",
      "startTime": 121.186,
      "duration": 2.3349999999999937
    },
    {
      "zh": "当然，你们可以用剩余的面包喂他们。",
      "en": "Yes, you can feed them the rest of the bread.",
      "startTime": 123.622,
      "duration": 3.146000000000001
    },
    {
      "zh": "佩奇和乔治喜欢喂面包给鸭子。",
      "en": "Peppa and George love feeding bread to ducks.",
      "startTime": 129.928,
      "duration": 2.591000000000008
    },
    {
      "zh": "妈妈，我想他们想要更多一些。",
      "en": "Mummy, I think they want some more.",
      "startTime": 138.57,
      "duration": 2.646000000000015
    },
    {
      "zh": "这是最后一块面包了。",
      "en": "That was the last of the bread.",
      "startTime": 141.33,
      "duration": 1.6529999999999916
    },
    {
      "zh": "我相信他们已经吃饱了。",
      "en": "I'm sure they've had enough.",
      "startTime": 143.41,
      "duration": 1.6330000000000098
    },
    {
      "zh": "对不起，鸭子女士，我们没有更多的面包了。",
      "en": "Sorry, Mrs. Duck, We've no more bread.",
      "startTime": 145.782,
      "duration": 3.133999999999986
    },
    {
      "zh": "鸭子们想要更多的食物。",
      "en": "The ducks want more food.",
      "startTime": 152.436,
      "duration": 1.579999999999984
    },
    {
      "zh": "猪爸爸只是嘴上说说要锻炼！",
      "en": "So much for Daddy Pig and his exercise!",
      "startTime": 156.288,
      "duration": 2.9739999999999895
    },
    {
      "zh": "呃？怎么了？",
      "en": "Eh? what?",
      "startTime": 160.661,
      "duration": 1.507000000000005
    },
    {
      "zh": "你们又来了！",
      "en": "You lot again!",
      "startTime": 164.402,
      "duration": 1.15300000000002
    },
    {
      "zh": "佩奇已经告诉你们，没有面包了！",
      "en": "Peppa told you, there's no more bread!",
      "startTime": 165.968,
      "duration": 2.5200000000000102
    },
    {
      "zh": "妈妈，我们还有草莓蛋糕嘛！",
      "en": "Mummy, we do have strawberry cake!",
      "startTime": 169.101,
      "duration": 3.1539999999999964
    },
    {
      "zh": "好的，如果有剩余的蛋糕，",
      "en": "Well, if there's any cake left over,",
      "startTime": 172.337,
      "duration": 2.240000000000009
    },
    {
      "zh": "你可以分些给鸭子们。",
      "en": "you can give it to the ducks.",
      "startTime": 174.797,
      "duration": 1.3660000000000139
    },
    {
      "zh": "每个人都喜欢猪妈妈亲手做的草莓蛋糕！",
      "en": "Everyone likes Mummy Pig's home-made strawberry cake!",
      "startTime": 177.176,
      "duration": 3.180000000000007
    },
    {
      "zh": "一只黄蜂！",
      "en": "Eeek! A wasp!",
      "startTime": 180.813,
      "duration": 1.436000000000007
    },
    {
      "zh": "我讨厌黄蜂！",
      "en": "I hate wasps! Shooooo!",
      "startTime": 182.589,
      "duration": 1.9470000000000027
    },
    {
      "zh": "它只是一只小小的黄蜂而已！",
      "en": "What a fuss, Mummy Pig!",
      "startTime": 184.949,
      "duration": 1.9329999999999927
    },
    {
      "zh": "它只是一只小小的黄蜂而已！",
      "en": "It's only a little wasp!",
      "startTime": 187.122,
      "duration": 1.4539999999999793
    },
    {
      "zh": "走开，黄蜂！",
      "en": "Go away, wasp!",
      "startTime": 188.876,
      "duration": 1.0529999999999973
    },
    {
      "zh": "只要呆着别动，猪妈妈。",
      "en": "Just stay still, Mummy Pig.",
      "startTime": 190.922,
      "duration": 1.5200000000000102
    },
    {
      "zh": "然后它就会飞走的。",
      "en": "Then it will fly away.",
      "startTime": 192.489,
      "duration": 1.2549999999999955
    },
    {
      "zh": "飞走了！你看，你只要呆着别动就行了！",
      "en": "There! You see, all you had to do is stay still!",
      "startTime": 195.973,
      "duration": 2.9199999999999875
    },
    {
      "zh": "快走开！",
      "en": "Eh! Get away!",
      "startTime": 199.431,
      "duration": 2.0719999999999743
    },
    {
      "zh": "滚开！呜啊。。。救命！呜啊~~！",
      "en": "Scram! Whoa... Help! Whooooaaa!",
      "startTime": 202.202,
      "duration": 3.1340000000000146
    },
    {
      "zh": "不要跟着我！",
      "en": "Shhooo! Get it off me! Whoooa! Arrgh!",
      "startTime": 207.736,
      "duration": 1.0800000000000125
    },
    {
      "zh": "我希望黄蜂没有叮到爸爸。",
      "en": "I hope the wasp doesn't sting Daddy.",
      "startTime": 209.696,
      "duration": 2.1140000000000043
    },
    {
      "zh": "快走开，你这只小虫子！",
      "en": "Get away, you little pest!",
      "startTime": 212.476,
      "duration": 2.086999999999989
    },
    {
      "zh": "不会的，爸爸跑得很快黄蜂追不上他。",
      "en": "No, Daddy is running too fast for the wasp to catch him.",
      "startTime": 214.986,
      "duration": 3.5200000000000102
    },
    {
      "zh": "Whoooa! Arrgh! Shooo!",
      "en": "Whoooa! Arrgh! Shooo!",
      "startTime": 218.656,
      "duration": 1.9170000000000016
    },
    {
      "zh": "趁黄蜂还没回来，我们吃蛋糕吧。",
      "en": "Let's eat our cake before the wasp comes back.",
      "startTime": 220.632,
      "duration": 3.1599999999999966
    },
    {
      "zh": "哦，不！我们忘记留些给鸭子们了！",
      "en": "Oh, no! we forgot to leave  any for the ducks!",
      "startTime": 230.35,
      "duration": 2.8600000000000136
    },
    {
      "zh": "我想我甩掉它了!",
      "en": "I think I lost it!",
      "startTime": 236.07,
      "duration": 1.406000000000006
    },
    {
      "zh": "你不是说过你要跑跑做些运动的吗？",
      "en": "You said you would run around and get some exercise,",
      "startTime": 238.002,
      "duration": 2.219999999999999
    },
    {
      "zh": "猪爸爸！但是我没有想到你真的做到了！",
      "en": "Daddy Pig! But I didn't believe you'd do it!",
      "startTime": 240.294,
      "duration": 2.674999999999983
    },
    {
      "zh": "幸好，我紧紧抓住了我的草莓蛋糕！",
      "en": "Luckily, I managed to hang on to my slice of strawberry cake!",
      "startTime": 246.725,
      "duration": 3.8000000000000114
    },
    {
      "zh": "等下，爸爸！",
      "en": "Stop, Daddy!",
      "startTime": 250.869,
      "duration": 1.2620000000000005
    },
    {
      "zh": "我们答应了剩下的蛋糕要分给鸭子们的！",
      "en": "We promised the rest of the cake for the ducks!",
      "startTime": 252.697,
      "duration": 2.1610000000000014
    },
    {
      "zh": "哦。",
      "en": "Oh.",
      "startTime": 255.606,
      "duration": 0.5570000000000164
    },
    {
      "zh": "你们真是很幸运的鸭子。",
      "en": "You are very lucky ducks.",
      "startTime": 257.941,
      "duration": 2.069000000000017
    },
    {
      "zh": "向猪爸爸说声“谢谢!”",
      "en": "Say ''thank you'' to Daddy Pig.",
      "startTime": 262.3,
      "duration": 1.9599999999999795
    },
    {
      "zh": "你们不要客气！",
      "en": "You're most welcome.",
      "startTime": 266.091,
      "duration": 1.6820000000000164
    },
    {
      "zh": "是时候回家了。跟鸭子们说声再见。",
      "en": "It's time to go home. Say goodbye to the ducks.",
      "startTime": 269.473,
      "duration": 3.0399999999999636
    },
    {
      "zh": "再见，鸭子们。",
      "en": "Bye bye, ducks.",
      "startTime": 272.73,
      "duration": 1.2969999999999686
    },
    {
      "zh": "下次再见了！",
      "en": "See you next time!",
      "startTime": 275.407,
      "duration": 2.1520000000000437
    }
  ]
}