{
    "title": "第 49 集购物！ | Shopping!",
    "data": [
        {
            "zh": "购物！",
            "en": "Shopping!",
            "startTime": 19.752,
            "duration": 1.991
        },
        {
            "zh": "佩奇和乔治一起去购物！",
            "en": "Peppa and George are going shopping!",
            "startTime": 23.971,
            "duration": 2.617
        },
        {
            "zh": "佩奇和乔治喜欢购物。",
            "en": "Peppa and George like shopping.",
            "startTime": 28.527,
            "duration": 2.43
        },
        {
            "zh": "乔治喜欢坐在推车里。",
            "en": "George loves sitting in the trolley.",
            "startTime": 32.84,
            "duration": 2.188
        },
        {
            "zh": "佩奇也是。",
            "en": "So does Peppa.",
            "startTime": 37.277,
            "duration": 1.179
        },
        {
            "zh": "爸爸，我能也坐在推车里吗？",
            "en": "Daddy, can I sit in the trolley, too?",
            "startTime": 38.57,
            "duration": 3.287
        },
        {
            "zh": "对于推车来说你太大了，佩奇。",
            "en": "You're too big for the trolley, Peppa.",
            "startTime": 42.423,
            "duration": 2.388
        },
        {
            "zh": "哦！",
            "en": "Oh!",
            "startTime": 44.897,
            "duration": 0.796
        },
        {
            "zh": "但你可以帮忙购物。",
            "en": "But you can help with the shopping.",
            "startTime": 46.352,
            "duration": 1.433
        },
        {
            "zh": "哦，好的！",
            "en": "Oh, goody!",
            "startTime": 48.033,
            "duration": 0.796
        },
        {
            "zh": "我们已经列了四样东西在购物清单上。",
            "en": "We've got four things on the list.",
            "startTime": 49.896,
            "duration": 2.38
        },
        {
            "zh": "有番茄，意大利面，洋葱和水果。",
            "en": "Tomatoes, spaghetti, onions and fruit.",
            "startTime": 52.301,
            "duration": 3.968
        },
        {
            "zh": "我都能找到！",
            "en": "I'll find it all!",
            "startTime": 56.515,
            "duration": 1.194
        },
        {
            "zh": "走这边！",
            "en": "This way!",
            "startTime": 62.795,
            "duration": 0.728
        },
        {
            "zh": "佩奇和乔治都喜欢购物。",
            "en": "Peppa and George love shopping.",
            "startTime": 64.501,
            "duration": 2.412
        },
        {
            "zh": "佩奇，首先，我们需要些番茄。",
            "en": "Peppa, first, we need tomatoes.",
            "startTime": 69.341,
            "duration": 2.491
        },
        {
            "zh": "我看到了！我看到了！",
            "en": "I can see them! I can see them!",
            "startTime": 73.716,
            "duration": 2.627
        },
        {
            "zh": "这里有番茄，妈妈。",
            "en": "Here are the tomatoes, Mummy.",
            "startTime": 76.376,
            "duration": 1.827
        },
        {
            "zh": "做得好，佩奇！",
            "en": "Well done, Peppa!",
            "startTime": 78.228,
            "duration": 1.797
        },
        {
            "zh": "一，二，三，四。",
            "en": "One, two, three, four.",
            "startTime": 80.841,
            "duration": 4.42
        },
        {
            "zh": "现在，把他们放进推车里。",
            "en": "Now, put them in the trolley.",
            "startTime": 85.371,
            "duration": 1.49
        },
        {
            "zh": "我找到番茄了！",
            "en": "I found the tomatoes!",
            "startTime": 88.566,
            "duration": 2.607
        },
        {
            "zh": "做得好，佩奇。",
            "en": "Well done, Peppa.",
            "startTime": 91.824,
            "duration": 1.509
        },
        {
            "zh": "番茄，那么现在可以把它从清单里划去了。",
            "en": "Tomatoes, that's one thing off the list.",
            "startTime": 93.506,
            "duration": 3.254
        },
        {
            "zh": "清单里的下一样是什么？",
            "en": "What's next on the list?",
            "startTime": 97.269,
            "duration": 1.522
        },
        {
            "zh": "意大利面！",
            "en": "Spaghetti!",
            "startTime": 99.289,
            "duration": 1.371
        },
        {
            "zh": "说得对，乔治，",
            "en": "That's right, George,",
            "startTime": 101.994,
            "duration": 1.351
        },
        {
            "zh": "但应该叫意大利面。",
            "en": "but it's called spa-ghe-tti.",
            "startTime": 103.487,
            "duration": 2.16
        },
        {
            "zh": "意大利面是佩奇和乔治最喜欢吃的食物。",
            "en": "Spaghetti is Peppa and George's favorite food.",
            "startTime": 107.374,
            "duration": 2.901
        },
        {
            "zh": "我想知道意大利面在哪？",
            "en": "I wonder where the spaghetti is?",
            "startTime": 110.35,
            "duration": 1.87
        },
        {
            "zh": "我看见了！这边！",
            "en": "I can see it! This way!",
            "startTime": 112.245,
            "duration": 2.578
        },
        {
            "zh": "意大利面！看，妈妈！意大利面在这里。",
            "en": "Spaghetti! Look, Mummy! Here's the spaghetti.",
            "startTime": 115.2,
            "duration": 3.716
        },
        {
            "zh": "做得好，佩奇。",
            "en": "well done, Peppa.",
            "startTime": 119.152,
            "duration": 0.971
        },
        {
            "zh": "把意大利面放进推车里吧。",
            "en": "Let's put this spaghetti in the trolley.",
            "startTime": 120.201,
            "duration": 2.155
        },
        {
            "zh": "好的，妈妈。",
            "en": "Yes, Mummy.",
            "startTime": 122.381,
            "duration": 1.095
        },
        {
            "zh": "乔治，它叫意-大-利-面。",
            "en": "George, it's called spa-ghe-tti.",
            "startTime": 127.356,
            "duration": 5.206
        },
        {
            "zh": "清单的下一样是什么，佩奇？",
            "en": "What's next on the list, Peppa?",
            "startTime": 136.895,
            "duration": 1.72
        },
        {
            "zh": "薯片！",
            "en": "Crisps!",
            "startTime": 138.884,
            "duration": 0.918
        },
        {
            "zh": "薯片不在清单上。",
            "en": "Crisps are not on the list.",
            "startTime": 140.189,
            "duration": 2.05
        },
        {
            "zh": "我们有很多薯片在家里，佩奇。",
            "en": "We have plenty of crisps at home, Peppa.",
            "startTime": 142.264,
            "duration": 2.357
        },
        {
            "zh": "再猜一下。",
            "en": "Have another guess.",
            "startTime": 144.769,
            "duration": 0.967
        },
        {
            "zh": "嗯。我真的想不起来了。",
            "en": "Hmmm. I just can't remember.",
            "startTime": 146.116,
            "duration": 3.588
        },
        {
            "zh": "你记得吗，乔治？",
            "en": "Can you remember, George?",
            "startTime": 149.85,
            "duration": 1.386
        },
        {
            "zh": "恐-龙！",
            "en": "Dine-Saw!",
            "startTime": 151.409,
            "duration": 0.986
        },
        {
            "zh": "恐龙？",
            "en": "Dinosaur?",
            "startTime": 152.549,
            "duration": 0.911
        },
        {
            "zh": "乔治，超市里可没有什么恐龙！",
            "en": "George, there aren't any dinosaurs in the supermarket!",
            "startTime": 153.759,
            "duration": 4.664
        },
        {
            "zh": "不，乔治。清单的下一样是洋葱。",
            "en": "No, George. The next thing on the Iist is onions.",
            "startTime": 160.783,
            "duration": 4.404
        },
        {
            "zh": "是洋葱！我现在想起来了！",
            "en": "Onions! I remember now!",
            "startTime": 165.27,
            "duration": 3.42
        },
        {
            "zh": "它们在这呢！",
            "en": "Here they are!",
            "startTime": 169.315,
            "duration": 1.024
        },
        {
            "zh": "做得好。",
            "en": "Well done.",
            "startTime": 171.61,
            "duration": 1.004
        },
        {
            "zh": "一，二，三，四！洋葱来了。",
            "en": "One, two, three, four! Onions.",
            "startTime": 173.685,
            "duration": 7.98
        },
        {
            "zh": "做得好。清单上的东西差不多都有了。",
            "en": "Very good.That's nearly everything on our list.",
            "startTime": 181.994,
            "duration": 3.675
        },
        {
            "zh": "清单上还有最后一样东西。",
            "en": "There's one last thing on the list.",
            "startTime": 185.807,
            "duration": 2.169
        },
        {
            "zh": "一棵植物？清单上有吗？",
            "en": "A plant? Is that on the list?",
            "startTime": 191.056,
            "duration": 2.628
        },
        {
            "zh": "哦，不，乔治。",
            "en": "Oh, no, George.",
            "startTime": 193.786,
            "duration": 1.776
        },
        {
            "zh": "清单上最后一样东西是水果。",
            "en": "The last thing on the list is fruit.",
            "startTime": 195.862,
            "duration": 2.287
        },
        {
            "zh": "哦。",
            "en": "Oh.",
            "startTime": 198.503,
            "duration": 0.659
        },
        {
            "zh": "没关系，乔治。水果由你来选。",
            "en": "Never mind, George. You can choose the fruit.",
            "startTime": 199.685,
            "duration": 2.946
        },
        {
            "zh": "水果在哪？",
            "en": "Where is the fruit?",
            "startTime": 204.018,
            "duration": 1.379
        },
        {
            "zh": "在那边！",
            "en": "Over there!",
            "startTime": 205.645,
            "duration": 0.908
        },
        {
            "zh": "那边有苹果，橙子，香蕉",
            "en": "There are apples and oranges and bananas",
            "startTime": 208.173,
            "duration": 3.094
        },
        {
            "zh": "还有一个很大的西瓜。",
            "en": "and a very big melon.",
            "startTime": 211.293,
            "duration": 2.154
        },
        {
            "zh": "想吃什么水果，乔治？",
            "en": "What fruit shall we have, George?",
            "startTime": 213.873,
            "duration": 2.492
        },
        {
            "zh": "苹果？",
            "en": "Apples?",
            "startTime": 216.768,
            "duration": 0.779
        },
        {
            "zh": "橙子？",
            "en": "Oranges?",
            "startTime": 217.883,
            "duration": 0.752
        },
        {
            "zh": "香蕉？",
            "en": "Bananas?",
            "startTime": 219.145,
            "duration": 1.058
        },
        {
            "zh": "一个西瓜！",
            "en": "A melon!",
            "startTime": 221.521,
            "duration": 1.06
        },
        {
            "zh": "这里是收银台，所有食物都在这里付钱。",
            "en": "This is the checkout where all the food is paid for.",
            "startTime": 228.381,
            "duration": 2.839
        },
        {
            "zh": "有番茄，意大利面，洋葱，西瓜，巧克力蛋糕。。。",
            "en": "Tomatoes, spaghetti, onions, melon, chocolate cake...",
            "startTime": 232.09,
            "duration": 9.808
        },
        {
            "zh": "巧克力蛋糕？",
            "en": "Chocolate cake?",
            "startTime": 242.073,
            "duration": 1.544
        },
        {
            "zh": "巧克力蛋糕？是在清单上的吗？",
            "en": "Chocolate cake? Is that on the list?",
            "startTime": 243.853,
            "duration": 2.785
        },
        {
            "zh": "佩奇？是你把巧克力蛋糕放进推车的吗？",
            "en": "Peppa? Did you put the chocolate cake in the trolley?",
            "startTime": 246.825,
            "duration": 3.436
        },
        {
            "zh": "不是，妈妈。",
            "en": "No, Mummy.",
            "startTime": 250.509,
            "duration": 0.989
        },
        {
            "zh": "乔治？是你把巧克力蛋糕放进推车的吗？",
            "en": "George? Did you put the chocolate cake in the trolley?",
            "startTime": 251.87,
            "duration": 3.231
        },
        {
            "zh": "不是。",
            "en": "No.",
            "startTime": 255.281,
            "duration": 0.625
        },
        {
            "zh": "哦，也不是我放的。",
            "en": "Well, I didn't put it in.",
            "startTime": 256.361,
            "duration": 1.433
        },
        {
            "zh": "那是谁放的？",
            "en": "Then who did?",
            "startTime": 257.99,
            "duration": 1.205
        },
        {
            "zh": "我想它配布丁吃很不错。",
            "en": "I thought it might be nice for pudding.",
            "startTime": 260.143,
            "duration": 3.7
        },
        {
            "zh": "猪爸爸！",
            "en": "Daddy Pig!",
            "startTime": 263.916,
            "duration": 1.3
        },
        {
            "zh": "淘气的爸爸！",
            "en": "Naughty Daddy!",
            "startTime": 266.218,
            "duration": 1.558
        },
        {
            "zh": "对不起！但它看上去很好吃。",
            "en": "Sorry! It just looked so delicious.",
            "startTime": 267.801,
            "duration": 3.326
        },
        {
            "zh": "它看上去的确很美味。",
            "en": "It does look rather yummy.",
            "startTime": 271.276,
            "duration": 1.797
        },
        {
            "zh": "哦，让我们假装它也在清单上。",
            "en": "Oh, let's pretend it was on the list.",
            "startTime": 273.519,
            "duration": 2.339
        },
        {
            "zh": "巧克力蛋糕。",
            "en": "Chocolate cake.",
            "startTime": 276.135,
            "duration": 1.365
        },
        {
            "zh": "好哦！",
            "en": "Hurray!",
            "startTime": 277.797,
            "duration": 0.989
        }
    ]
}